django_epflmisc/__init__.py
django_epflmisc/decorators.py
tests/__init__.py
tests/manage.py
tests/settings.py
tests/test_decorators.py
django_epfl_misc-2.0.0.dist-info/LICENSE
django_epfl_misc-2.0.0.dist-info/METADATA
django_epfl_misc-2.0.0.dist-info/WHEEL
django_epfl_misc-2.0.0.dist-info/top_level.txt
django_epfl_misc-2.0.0.dist-info/RECORD
