Metadata-Version: 2.1
Name: django-epfl-misc
Version: 2.0.0
Summary: A Django application with helper functions and utilities.
Home-page: https://github.com/epfl-si/django-epfl-misc
Author: William Belle
Author-email: william.belle@gmail.com
License: MIT
Project-URL: Changelog, https://github.com/epfl-si/django-epfl-misc/blob/main/CHANGELOG.md
Project-URL: Source, https://github.com/epfl-si/django-epfl-misc
Project-URL: Tracker, https://github.com/epfl-si/django-epfl-misc/issues
Platform: UNKNOWN
Classifier: Environment :: Web Environment
Classifier: Framework :: Django
Classifier: Framework :: Django :: 2.2
Classifier: Framework :: Django :: 3.2
Classifier: Framework :: Django :: 4.2
Classifier: Framework :: Django :: 5.2
Classifier: Intended Audience :: Developers
Classifier: License :: OSI Approved :: MIT License
Classifier: Operating System :: OS Independent
Classifier: Programming Language :: Python
Classifier: Programming Language :: Python :: 3
Classifier: Programming Language :: Python :: 3.7
Classifier: Programming Language :: Python :: 3.8
Classifier: Programming Language :: Python :: 3.9
Classifier: Programming Language :: Python :: 3.10
Classifier: Programming Language :: Python :: 3.11
Classifier: Programming Language :: Python :: 3.12
Classifier: Programming Language :: Python :: 3.13
Classifier: Topic :: Utilities
Requires-Python: >=3.7
